Metadata-Version: 1.0
Name: eleme.openapi.sdk
Version: 0.0.1.13
Summary: eleme openapi python sdk
Home-page: UNKNOWN
Author: david
Author-email: pengfei.zhu@ele.me
License: MIT License
Keywords: eleme,openapi
Platform: UNKNOWN
